dm2022exp/__init__.py
dm2022exp-1.0.0.dist-info/METADATA
dm2022exp-1.0.0.dist-info/WHEEL
dm2022exp-1.0.0.dist-info/top_level.txt
dm2022exp-1.0.0.dist-info/RECORD
