Metadata-Version: 2.1
Name: dm2022exp
Version: 1.0.0
Summary: experimental package of HZAU 2022 data mining course
Author: HuChang
Author-email: changlehung@gmail.com
